<annotation>
	<folder>JPEGImages</folder>
	<filename>a03935fe-1009-4940-a8d4-0f610757424d.jpg</filename>
	<path>F:\Reflective_vests\VOC2021\JPEGImages\a03935fe-1009-4940-a8d4-0f610757424d.jpg</path>
	<source>
		<database>Unknown</database>
	</source>
	<size>
		<width>500</width>
		<height>350</height>
		<depth>3</depth>
	</size>
	<segmented>0</segmented>
	<object>
		<name>other_clothes</name>
		<pose>Unspecified</pose>
		<truncated>0</truncated>
		<difficult>0</difficult>
		<bndbox>
			<xmin>291</xmin>
			<ymin>93</ymin>
			<xmax>445</xmax>
			<ymax>277</ymax>
		</bndbox>
	</object>
	<object>
		<name>reflective_clothes</name>
		<pose>Unspecified</pose>
		<truncated>0</truncated>
		<difficult>0</difficult>
		<bndbox>
			<xmin>18</xmin>
			<ymin>54</ymin>
			<xmax>207</xmax>
			<ymax>291</ymax>
		</bndbox>
	</object>
	<object>
		<name>reflective_clothes</name>
		<pose>Unspecified</pose>
		<truncated>0</truncated>
		<difficult>0</difficult>
		<bndbox>
			<xmin>195</xmin>
			<ymin>3</ymin>
			<xmax>287</xmax>
			<ymax>128</ymax>
		</bndbox>
	</object>
</annotation>
